Metadata-Version: 2.1
Name: WikiClosetClient
Version: 0.0.7
Summary: Tools for wiki.gg staff
Home-page: https://github.com/RheingoldRiver/WikiClosetClient
Author: RheingoldRiver
Author-email: river.esports@gmail.com
Requires-Python: >=3.6
Requires-Dist: mwcleric>=0.10.2
